Codes/Counter/Sync/Up/TFF.v
module TFF(d,clk,reset,q);
input clk, reset;
input wire d;
output reg q;

initial 
	q = 1'b0;

always@(posedge clk or posedge reset)
begin
	if(reset)
 		q <= 1'b0;
	else
		q <= (d&(~q)) | ((~d)&q);
end

endmodule

Codes/FlipFlops/TFF/TFF_tb.v
`include "TFF.v"

module TFF_tb;

reg d, clk, reset;
wire q;

initial
	begin
		$dumpfile("TFF_tb.vcd");
		$dumpvars(0, TFF_tb);
	end

TFF d1(d, clk, reset, q);


initial
	begin
		reset=0;
		clk =0;
		d=0;
		#20 reset=1;
	end

always #5  
	clk =  ! clk; 

always #10 
	d=~d;

always@(*)
	begin
 		$display("time:%t d=%b, clk=%b, rst=%b,q=%b\n", $time, d, clk, reset, q);
	end 

initial
	#100 $finish;
endmodule

Codes/FlipFlops/TFF/TFF_tb.vcd
$date
	Wed Aug 14 10:02:56 2019
$end
$version
	Icarus Verilog
$end
$timescale
	1s
$end
$scope module TFF_tb $end
$var wire 1 ! q $end
$var reg 1 " clk $end
$var reg 1 # d $end
$var reg 1 $ reset $end
$scope module d1 $end
$var wire 1 " clk $end
$var wire 1 # d $end
$var wire 1 $ reset $end
$var reg 1 ! q $end
$upscope $end
$upscope $end
$enddefinitions $end
#0
$dumpvars
0$
0#
0"
x!
$end
#5
1!
1"
#10
0"
1#
#15
0!
1"
#20
0"
0#
1$
#25
1"
#30
0"
1#
#35
1"
#40
0"
0#
#45
1"
#50
0"
1#
#55
1"
#60
0"
0#
#65
1"
#70
0"
1#
#75
1"
#80
0"
0#
#85
1"
#90
0"
1#
#95
1"
#100
0"
0#
