Codes/Counter/Sync/Up/TFF.v
module TFF(d,clk,reset,q);
input clk, reset;
input wire d;
output reg q;

initial 
	q = 1'b0;

always@(posedge clk or posedge reset)
begin
	if(reset)
 		q <= 1'b0;
	else
		q <= (d&(~q)) | ((~d)&q);
end

endmodule

Codes/Counter/Sync/Down/DownSync.v
`include "TFF.v"

module DownSync(clk,reset,q);
input clk, reset;
output [4:1] q;

wire [4:1]inputs;

assign inputs[1] = 1'b1;

assign inputs[2] = ~q[1];
assign inputs[3] = (~q[1])&(~q[2]);
assign inputs[4] = (~q[1])&(~q[2])&(~q[3]);


TFF tff_1(inputs[1], clk, reset, q[1]);
TFF tff_2(inputs[2], clk, reset, q[2]);
TFF tff_3(inputs[3], clk, reset, q[3]);
TFF tff_4(inputs[4], clk, reset, q[4]);

endmodule

FlipFlops/Counter/Sync/Down/DownSync_tb.v
`include "DownSync.v"

module DownSync_tb;

reg clk, reset;
wire [4:1] q;

initial
	begin
		$dumpfile("DownSync_tb.vcd");
		$dumpvars(0, DownSync_tb);
	end

DownSync downSync(clk, reset, q);


initial
	begin
		reset=0;
		clk =0;
	end

always #5  
	clk =  ! clk; 

initial
	$monitor($time, ": clk=%b, rst=%b, q=%b\n", clk, reset, q);

initial
	#100 $finish;
endmodule

FlipFlops/Counter/Sync/Down/DownSync_tb.vcd
$date
	Fri Aug 16 15:16:37 2019
$end
$version
	Icarus Verilog
$end
$timescale
	1s
$end
$scope module DownSync_tb $end
$var wire 4 ! q [4:1] $end
$var reg 1 " clk $end
$var reg 1 # reset $end
$scope module downSync $end
$var wire 1 " clk $end
$var wire 1 # reset $end
$var wire 4 $ q [4:1] $end
$var wire 4 % inputs [4:1] $end
$scope module tff_1 $end
$var wire 1 " clk $end
$var wire 1 & d $end
$var wire 1 # reset $end
$var reg 1 ' q $end
$upscope $end
$scope module tff_2 $end
$var wire 1 " clk $end
$var wire 1 ( d $end
$var wire 1 # reset $end
$var reg 1 ) q $end
$upscope $end
$scope module tff_3 $end
$var wire 1 " clk $end
$var wire 1 * d $end
$var wire 1 # reset $end
$var reg 1 + q $end
$upscope $end
$scope module tff_4 $end
$var wire 1 " clk $end
$var wire 1 , d $end
$var wire 1 # reset $end
$var reg 1 - q $end
$upscope $end
$upscope $end
$upscope $end
$enddefinitions $end
#0
$dumpvars
1-
0,
1+
0*
1)
0(
1'
1&
b1 %
b1111 $
0#
0"
b1111 !
$end
#5
1(
b11 %
b1110 !
b1110 $
0'
1"
#10
0"
#15
0(
b1 %
0)
b1101 !
b1101 $
1'
1"
#20
0"
#25
1*
1(
b111 %
b1100 !
b1100 $
0'
1"
#30
0"
#35
0*
0(
b1 %
0+
1)
b1011 !
b1011 $
1'
1"
#40
0"
#45
1(
b11 %
b1010 !
b1010 $
0'
1"
#50
0"
#55
0(
b1 %
0)
b1001 !
b1001 $
1'
1"
#60
0"
#65
1,
1*
1(
b1111 %
b1000 !
b1000 $
0'
1"
#70
0"
#75
0,
0*
0(
b1 %
0-
1+
1)
b111 !
b111 $
1'
1"
#80
0"
#85
1(
b11 %
b110 !
b110 $
0'
1"
#90
0"
#95
0(
b1 %
0)
b101 !
b101 $
1'
1"
