FlipFlops/DFF/DFF.v
module DFF(d,clk,reset,q);
input d, clk, reset;
output q;
reg q;

always@(negedge clk or negedge reset)
	if(reset)
 		q <= 1'b0;
	else
		q <= d;

endmodule

Codes/Register/SR_PIPO.v
`include "DFF.v"

module SR_PIPO(d,clk,reset,outputs, write_check);

input [4:1]d;
input write_check;
input clk, reset;

wire w[3:1];

output [4:1]outputs;

assign w[1] = (write_check&d[1]) | ((~write_check)&outputs[1]);
assign w[2] = (write_check&d[2]) | ((~write_check)&outputs[2]);
assign w[3] = (write_check&d[3]) | ((~write_check)&outputs[3]);

DFF dff_1(d[1], clk, reset, outputs[1]);
DFF dff_2(w[1], clk, reset, outputs[2]);
DFF dff_3(w[2], clk, reset, outputs[3]);
DFF dff_4(w[3], clk, reset, outputs[4]);

endmodule

Codes/Register/SR_PIPO_tb.v
`include "SR_PIPO.v"

module SR_PIPO_tb;

reg clk, reset, write;
wire [4:1] q;

reg [4:1] inp;

initial
	begin
		$dumpfile("SR_PIPO_tb.vcd");
		$dumpvars(0, SR_PIPO_tb);
	end

SR_PIPO srPIPO(inp, clk, reset, q, write);


initial
	begin
		reset=0;
		clk =0;
		write = 1;

		inp = 4'b0000;
		#5 write = 1;inp = 4'b0010;
		#5 write = 0;inp = 4'b0001;
		#5 write = 1;inp = 4'b1010;
		#5 write = 0;inp = 4'b0000;
		#5 write = 0;inp = 4'b0110;
		#5 write = 0;inp = 4'b0001;
		#5 write = 0;inp = 4'b0010;
		#5 write = 0;inp = 4'b0000;
		#5 write = 1;inp = 4'b0010;
		#5 write = 0;inp = 4'b0001;
	end

always #5  
	clk =  ! clk; 

initial
	$monitor($time, ": clk=%b, rst=%b, inp=%b, q=%b\n", clk, reset, inp, q);

initial
	#100 $finish;

endmodule

FlipFlops/Register/SR_PIPO_tb.vcd
$date
	Thu Aug 15 16:06:40 2019
$end
$version
	Icarus Verilog
$end
$timescale
	1s
$end
$scope module SR_PIPO_tb $end
$var wire 4 ! q [4:1] $end
$var reg 1 " clk $end
$var reg 4 # inp [4:1] $end
$var reg 1 $ reset $end
$var reg 1 % write $end
$scope module srPIPO $end
$var wire 1 " clk $end
$var wire 4 & d [4:1] $end
$var wire 1 $ reset $end
$var wire 1 % write_check $end
$var wire 4 ' outputs [4:1] $end
$scope module dff_1 $end
$var wire 1 " clk $end
$var wire 1 ( d $end
$var wire 1 $ reset $end
$var reg 1 ) q $end
$upscope $end
$scope module dff_2 $end
$var wire 1 " clk $end
$var wire 1 * d $end
$var wire 1 $ reset $end
$var reg 1 + q $end
$upscope $end
$scope module dff_3 $end
$var wire 1 " clk $end
$var wire 1 , d $end
$var wire 1 $ reset $end
$var reg 1 - q $end
$upscope $end
$scope module dff_4 $end
$var wire 1 " clk $end
$var wire 1 . d $end
$var wire 1 $ reset $end
$var reg 1 / q $end
$upscope $end
$upscope $end
$upscope $end
$enddefinitions $end
#0
$dumpvars
x/
0.
x-
0,
x+
0*
x)
0(
bx '
b0 &
1%
0$
b0 #
0"
bx !
$end
#5
1,
1"
b10 #
b10 &
#10
0/
1-
0+
b101 !
b101 '
1)
1*
1.
0,
1(
0"
b1 #
b1 &
0%
#15
0*
1,
0.
0(
1"
b1010 #
b1010 &
1%
#20
b100 !
b100 '
0)
0*
1.
0,
0"
b0 #
b0 &
0%
#25
1"
b110 #
b110 &
#30
0.
1*
1/
0-
b1001 !
b1001 '
1)
1(
0"
b1 #
b1 &
#35
0(
1"
b10 #
b10 &
#40
0*
1,
0)
1+
b10 !
b10 '
0/
0"
b0 #
b0 &
#45
1"
b10 #
b10 &
1%
#50
1.
0,
1*
1-
0+
b101 !
b101 '
1)
1(
0"
b1 #
b1 &
0%
#55
1"
#60
1,
0.
1+
0-
b1011 !
b1011 '
1/
0"
#65
1"
#70
1.
0/
b111 !
b111 '
1-
0"
#75
1"
#80
b1111 !
b1111 '
1/
0"
