Codes/Register/DFF.v
module DFF(d,clk,reset,q);
input clk, reset;
input wire d;
output reg q;

always@(negedge clk or posedge reset)
begin
	if(reset)
 		q <= 1'b0;
	else
		q <= d;
end

endmodule

Codes/Register/SR_SIPO.v
`include "DFF.v"

module SR_SIPO(d,clk,reset,q);

input d, clk, reset;
output [4:1] q;

DFF dff_1(d, clk, reset, q[1]);
DFF dff_2(q[1], clk, reset, q[2]);
DFF dff_3(q[2], clk, reset, q[3]);
DFF dff_4(q[3], clk, reset, q[4]);

endmodule

FlipFlops/Register/SR_SIPO_tb.v
`include "SR_SIPO.v"

module SR_SIPO_tb;

reg clk, reset;
wire [4:1] q;

reg inp;

initial
	begin
		$dumpfile("SR_SIPO_tb.vcd");
		$dumpvars(0, SR_SIPO_tb);
	end

SR_SIPO srSIPO(inp, clk, reset, q);


initial
	begin
		inp = 0;
		reset=0;
		clk =0;
	end

always@(negedge clk)
	inp = ~inp;

always #5  
	clk =  ! clk; 

initial
	$monitor($time, ": clk=%b, rst=%b, inp=%b, q=%b\n", clk, reset, inp, q);

initial
	#100 $finish;

endmodule

Codes/Register/SR_SIPO_tb.vcd
$date
	Thu Aug 15 15:43:51 2019
$end
$version
	Icarus Verilog
$end
$timescale
	1s
$end
$scope module SR_SIPO_tb $end
$var wire 4 ! q [4:1] $end
$var reg 1 " clk $end
$var reg 1 # inp $end
$var reg 1 $ reset $end
$scope module srSIPO $end
$var wire 1 " clk $end
$var wire 1 # d $end
$var wire 1 $ reset $end
$var wire 4 % q [4:1] $end
$scope module dff_1 $end
$var wire 1 " clk $end
$var wire 1 # d $end
$var wire 1 $ reset $end
$var reg 1 & q $end
$upscope $end
$scope module dff_2 $end
$var wire 1 " clk $end
$var wire 1 ' d $end
$var wire 1 $ reset $end
$var reg 1 ( q $end
$upscope $end
$scope module dff_3 $end
$var wire 1 " clk $end
$var wire 1 ) d $end
$var wire 1 $ reset $end
$var reg 1 * q $end
$upscope $end
$scope module dff_4 $end
$var wire 1 " clk $end
$var wire 1 + d $end
$var wire 1 $ reset $end
$var reg 1 , q $end
$upscope $end
$upscope $end
$upscope $end
$enddefinitions $end
#0
$dumpvars
x,
x+
x*
x)
x(
0'
0&
bx0 %
0$
0#
0"
bx0 !
$end
#5
1"
#10
0)
1'
0(
bx01 !
bx01 %
1&
1#
0"
#15
1"
#20
0'
1)
0+
0&
1(
bx010 !
bx010 %
0*
0#
0"
#25
1"
#30
1+
0)
1'
0,
1*
0(
b101 !
b101 %
1&
1#
0"
#35
1"
#40
0'
1)
0+
0&
1(
0*
b1010 !
b1010 %
1,
0#
0"
#45
1"
#50
1+
0)
1'
0,
1*
0(
b101 !
b101 %
1&
1#
0"
#55
1"
#60
0'
1)
0+
0&
1(
0*
b1010 !
b1010 %
1,
0#
0"
#65
1"
#70
1+
0)
1'
0,
1*
0(
b101 !
b101 %
1&
1#
0"
#75
1"
#80
0'
1)
0+
0&
1(
0*
b1010 !
b1010 %
1,
0#
0"
#85
1"
#90
1+
0)
1'
0,
1*
0(
b101 !
b101 %
1&
1#
0"
#95
1"
#100
0'
1)
0+
0&
1(
0*
b1010 !
b1010 %
1,
0#
0"
