Codes/Counter/ASync/DFF.v
module DFF(d,clk,reset,q);
input clk, reset;
input wire d;
output reg q;

initial 
	q = 1'b0;

always@(posedge clk or posedge reset)
begin
	if(reset)
 		q <= 1'b0;
	else
		q <= d;
end

endmodule

Codes/Counter/ASync/DownASync.v
`include "DFF.v"

module DownASync(clk,reset,q);
input clk, reset;
output [4:1] q;

DFF dff_1(~q[1], clk, reset, q[1]);
DFF dff_2(~q[2], q[1], reset, q[2]);
DFF dff_3(~q[3], q[2], reset, q[3]);
DFF dff_4(~q[4], q[3], reset, q[4]);

endmodule

Codes/Counter/ASync/DownASync_tb.v
`include "DownASync.v"

module DownASync_tb;

reg clk, reset;
wire [4:1] q;

initial
	begin
		$dumpfile("DownASync_tb.vcd");
		$dumpvars(0, DownASync_tb);
	end

DownASync Downasync(clk, reset, q);


initial
	begin
		reset=0;
		clk =0;
	end

always #5  
	clk =  ! clk; 

initial
	$monitor($time, ": clk=%b, rst=%b,q=%b\n", clk, reset, q);

initial
	#100 $finish;
endmodule

Codes/Counter/ASync/DownASync_tb.vcd
$date
	Thu Aug 15 15:15:35 2019
$end
$version
	Icarus Verilog
$end
$timescale
	1s
$end
$scope module DownASync_tb $end
$var wire 4 ! q [4:1] $end
$var reg 1 " clk $end
$var reg 1 # reset $end
$scope module Downasync $end
$var wire 1 " clk $end
$var wire 1 # reset $end
$var wire 4 $ q [4:1] $end
$scope module dff_1 $end
$var wire 1 " clk $end
$var wire 1 % d $end
$var wire 1 # reset $end
$var reg 1 & q $end
$upscope $end
$scope module dff_2 $end
$var wire 1 ' clk $end
$var wire 1 ( d $end
$var wire 1 # reset $end
$var reg 1 ) q $end
$upscope $end
$scope module dff_3 $end
$var wire 1 * clk $end
$var wire 1 + d $end
$var wire 1 # reset $end
$var reg 1 , q $end
$upscope $end
$scope module dff_4 $end
$var wire 1 - clk $end
$var wire 1 . d $end
$var wire 1 # reset $end
$var reg 1 / q $end
$upscope $end
$upscope $end
$upscope $end
$enddefinitions $end
#0
$dumpvars
0/
1.
0-
0,
1+
0*
0)
1(
0'
0&
1%
b0 $
0#
0"
b0 !
$end
#5
0.
1/
0+
1-
1,
0(
1*
1)
0%
1'
b1111 !
b1111 $
1&
1"
#10
0"
#15
1%
0'
b1110 !
b1110 $
0&
1"
#20
0"
#25
1(
0*
0)
0%
1'
b1101 !
b1101 $
1&
1"
#30
0"
#35
1%
0'
b1100 !
b1100 $
0&
1"
#40
0"
#45
1+
0-
0,
0(
1*
1)
0%
1'
b1011 !
b1011 $
1&
1"
#50
0"
#55
1%
0'
b1010 !
b1010 $
0&
1"
#60
0"
#65
1(
0*
0)
0%
1'
b1001 !
b1001 $
1&
1"
#70
0"
#75
1%
0'
b1000 !
b1000 $
0&
1"
#80
0"
#85
1.
0/
0+
1-
1,
0(
1*
1)
0%
1'
b111 !
b111 $
1&
1"
#90
0"
#95
1%
0'
b110 !
b110 $
0&
1"
